{
  "temporarias": [
    {
      "key": "white-mensal-asd12345",
      "expira_em": "2025-08-03T00:00:00"
    },
    {
      "key": "neves-mensal-uhayrb",
      "expira_em": "2025-08-03T16:11:35.664916Z"
    },
    {
      "key": "lucas",
      "expira_em": "2025-07-10T23:46:14.2530268Z"
    },
    {
      "key": "wh_lucas.paiva78",
      "expira_em": "2025-08-14T21:53:13.2028735Z"
    },
    {
      "key": "wh_kauanza56",
      "expira_em": "2025-07-22T22:36:38.5869528Z"
    },
    {
      "key": "wh_kuan",
      "expira_em": "2025-07-23T22:51:34.7919974Z"
    }
  ]
}